[{"hospital_name": "Advanta Hospital", "hospital_id": "02115a1a8d949217d7a1ce769a335bf1966f5537", "rating": 4.8, "latitude": 28.6025272, "reviews": [{"Review": "Hostpital is close house ", "id": 1485823603}, {"Review": "This is the only Multi Speciality hospital in jhajjar. ", "id": 1448591223}, {"Review": "First multi speciality Hospital in Jhajjar even Advanta Hospital providing all kind of facilities at such kind of place......Awesome...... That is good for Jhajjar and near by..villages.. ", "id": 1428309823}, {"Review": "Best hospital in jhajjar", "id": 1484120026}, {"Review": "Best Hospital in Jhajjar city", "id": 1451536116}], "longitude": 76.6575766, "address": "Silani Gate, Jhajjar, Haryana 124103, India", "international_phone_number": ""}]