{"html_attributions": [], "result": {"icon": "https://maps.gstatic.com/mapfiles/place_api/icons/doctor-71.png", "name": "Arya Children Hospital", "id": "2be74905c4e858e7cfe55b62196c7062335d262a", "address_components": [{"short_name": "Jhajjar", "long_name": "Jhajjar", "types": ["locality", "political"]}, {"short_name": "Jhajjar", "long_name": "Jhajjar", "types": ["administrative_area_level_2", "political"]}, {"short_name": "HR", "long_name": "Haryana", "types": ["administrative_area_level_1", "political"]}, {"short_name": "IN", "long_name": "India", "types": ["country", "political"]}, {"short_name": "124103", "long_name": "124103", "types": ["postal_code"]}], "types": ["hospital", "point_of_interest", "establishment"], "utc_offset": 330, "url": "https://maps.google.com/?cid=1302857073808160856", "adr_address": "<span class=\"locality\">Jhajjar</span>, <span class=\"region\">Haryana</span> <span class=\"postal-code\">124103</span>, <span class=\"country-name\">India</span>", "formatted_address": "Jhajjar, Haryana 124103, India", "reviews": [{"aspects": [{"rating": 2, "type": "overall"}], "author_url": "https://www.google.com/maps/contrib/114101750602871038669/reviews", "profile_photo_url": "https://lh4.googleusercontent.com/-Fs0vjxWSTig/AAAAAAAAAAI/AAAAAAAAAfw/lh3R-f4LHVg/s128-c0x00000000-cc-rp-mo-ba1/photo.jpg", "text": "", "author_name": "tarun kumar", "language": "en", "rating": 4, "time": 1484632567, "relative_time_description": "2 months ago"}, {"aspects": [{"rating": 3, "type": "overall"}], "author_url": "https://www.google.com/maps/contrib/103664040163514095202/reviews", "profile_photo_url": "https://lh6.googleusercontent.com/--IsIhzRcaKA/AAAAAAAAAAI/AAAAAAAAAAA/AMcAYi_chPB5q_KsHONlYvIabjEskObbAA/s128-c0x00000000-cc-rp-mo/photo.jpg", "text": "", "author_name": "kuldeep khandodiya", "language": "en", "rating": 5, "time": 1469942074, "relative_time_description": "7 months ago"}], "scope": "GOOGLE", "vicinity": "Jhajjar", "rating": 4.5, "reference": "CmRRAAAAbnViXvSUCks_Y6NQwmNcP_GMmYYJJG6yfe-ikZYzelwZ4vIJjUC8OZzVig0QqBpdg9B8eR6sOpNfCvllwUr31KiebGBSR9zf41_pvSs1wygBJN7JsFAOANN0oUR2rDZcEhDMfhy7CCiIfi6pcYohyYWeGhSEuymF90nQyidzWBpf-eRSae3WIA", "place_id": "ChIJXT2I-HtwDTkRWLhwFZutFBI", "geometry": {"viewport": {"southwest": {"lng": 76.64625081970848, "lat": 28.60647431970849}, "northeast": {"lng": 76.6489487802915, "lat": 28.6091722802915}}, "location": {"lng": 76.6475998, "lat": 28.60782329999999}}}, "status": "OK"}