{"html_attributions": [], "result": {"name": "Dr. K.C. Sachdeva Hospital", "id": "3c82c2215bee380be36c824625569c6f757aa2a5", "address_components": [{"short_name": "Karnal", "long_name": "Karnal", "types": ["locality", "political"]}, {"short_name": "Saini Colony", "long_name": "Saini Colony", "types": ["neighborhood", "political"]}, {"short_name": "Slum Area", "long_name": "Slum Area", "types": ["sublocality_level_2", "sublocality", "political"]}, {"short_name": "Sector 12", "long_name": "Sector 12", "types": ["sublocality_level_1", "sublocality", "political"]}, {"short_name": "Karnal", "long_name": "Karnal", "types": ["administrative_area_level_2", "political"]}, {"short_name": "HR", "long_name": "Haryana", "types": ["administrative_area_level_1", "political"]}, {"short_name": "IN", "long_name": "India", "types": ["country", "political"]}, {"short_name": "132001", "long_name": "132001", "types": ["postal_code"]}], "formatted_phone_number": "098130 69377", "types": ["hospital", "point_of_interest", "establishment"], "utc_offset": 330, "url": "https://maps.google.com/?cid=5991503710955845896", "adr_address": "Near Hospital Chowk, <span class=\"street-address\">Slum Area, Sector 12</span>, <span class=\"extended-address\">Saini Colony, Slum Area, Sector 12</span>, <span class=\"locality\">Karnal</span>, <span class=\"region\">Haryana</span> <span class=\"postal-code\">132001</span>, <span class=\"country-name\">India</span>", "formatted_address": "Near Hospital Chowk, Slum Area, Sector 12, Saini Colony, Slum Area, Sector 12, Karnal, Haryana 132001, India", "scope": "GOOGLE", "geometry": {"viewport": {"southwest": {"lng": 76.99593531970848, "lat": 29.6931600197085}, "northeast": {"lng": 76.99863328029149, "lat": 29.6958579802915}}, "location": {"lng": 76.99728429999999, "lat": 29.694509}}, "vicinity": "Near Hospital Chowk, Slum Area, Sector 12, Karnal", "place_id": "ChIJnZEilRxwDjkRCDn1eeEYJlM", "reference": "CmRRAAAA5LDo34G9mppQoyhE0Lkxzltz3HA3x8va8DIMUAurhUStnsWKBCPYT-jjKFIt7gU9DTkDeXWSB_Mc354dTNsZPSuEE_CumTR6APzUBDtepr784_3bz31Q0bjUyfGXtankEhBWsgWlVtIZz2AwFOtn8pDbGhRzHDqcv6WETxvwi-kH0nKILXJXPw", "icon": "https://maps.gstatic.com/mapfiles/place_api/icons/doctor-71.png", "international_phone_number": "+91 98130 69377"}, "status": "OK"}