{"html_attributions": [], "result": {"icon": "https://maps.gstatic.com/mapfiles/place_api/icons/doctor-71.png", "name": "Haryana Nursing Home Unit - 1", "id": "ce42c04ca473eb900f30bf6500ce4ce0b5f29472", "opening_hours": {"weekday_text": ["Monday: 10:00 AM \u2013 10:00 PM", "Tuesday: 10:00 AM \u2013 10:00 PM", "Wednesday: 10:00 AM \u2013 10:00 PM", "Thursday: 10:00 AM \u2013 10:00 PM", "Friday: 10:00 AM \u2013 10:00 PM", "Saturday: 10:00 AM \u2013 10:00 PM", "Sunday: 10:00 AM \u2013 10:00 PM"], "periods": [{"close": {"day": 0, "time": "2200"}, "open": {"day": 0, "time": "1000"}}, {"close": {"day": 1, "time": "2200"}, "open": {"day": 1, "time": "1000"}}, {"close": {"day": 2, "time": "2200"}, "open": {"day": 2, "time": "1000"}}, {"close": {"day": 3, "time": "2200"}, "open": {"day": 3, "time": "1000"}}, {"close": {"day": 4, "time": "2200"}, "open": {"day": 4, "time": "1000"}}, {"close": {"day": 5, "time": "2200"}, "open": {"day": 5, "time": "1000"}}, {"close": {"day": 6, "time": "2200"}, "open": {"day": 6, "time": "1000"}}], "open_now": false}, "address_components": [{"short_name": "SH 8", "long_name": "State Highway 8", "types": ["route"]}, {"short_name": "Sector 14", "long_name": "Sector 14", "types": ["sublocality_level_1", "sublocality", "political"]}, {"short_name": "Karnal", "long_name": "Karnal", "types": ["locality", "political"]}, {"short_name": "Karnal", "long_name": "Karnal", "types": ["administrative_area_level_2", "political"]}, {"short_name": "HR", "long_name": "Haryana", "types": ["administrative_area_level_1", "political"]}, {"short_name": "IN", "long_name": "India", "types": ["country", "political"]}, {"short_name": "132001", "long_name": "132001", "types": ["postal_code"]}], "types": ["hospital", "point_of_interest", "establishment"], "utc_offset": 330, "url": "https://maps.google.com/?cid=6942085478536681244", "adr_address": "<span class=\"street-address\">SH 8</span>, <span class=\"extended-address\">Sector 14</span>, <span class=\"locality\">Karnal</span>, <span class=\"region\">Haryana</span> <span class=\"postal-code\">132001</span>, <span class=\"country-name\">India</span>", "formatted_address": "SH 8, Sector 14, Karnal, Haryana 132001, India", "reviews": [{"aspects": [{"rating": 2, "type": "overall"}], "author_url": "https://www.google.com/maps/contrib/112060061250977197984/reviews", "profile_photo_url": "https://lh4.googleusercontent.com/-gZmevbIAD9k/AAAAAAAAAAI/AAAAAAAAANw/-AfF4jqW1lI/s128-c0x00000000-cc-rp-mo-ba1/photo.jpg", "text": "Dr. Veena katyal is soo nice of nature .... good staff....", "author_name": "Harvinder Singh", "language": "en", "rating": 4, "time": 1469009970, "relative_time_description": "8 months ago"}], "scope": "GOOGLE", "vicinity": "State Highway 8, Sector 14, Karnal", "rating": 4, "reference": "CmRRAAAAPJ9zqk9hQu7IbKhXYIGBs_UWonhHS07vYtOBiOJr2efWXf389RPoWpTcAECtnUVPWwEdX6DNvDqgqA67I4JY_dHDLDT_sLYMUv625_Ion-LgAaOi5GpZCpV263L8WeBrEhBCH7VTGcrfm-yuT-dhEPGfGhStXsJ281Jy-8MH9yCJkJfwtdBN5g", "place_id": "ChIJN91vhRFwDjkRHJeTRPY9V2A", "geometry": {"viewport": {"southwest": {"lng": 76.99531576970848, "lat": 29.6810954697085}, "northeast": {"lng": 76.9980137302915, "lat": 29.68379343029149}}, "location": {"lng": 76.996653, "lat": 29.68232009999999}}}, "status": "OK"}