[{"hospital_name": "Sunderlal Jain Hospital", "hospital_id": "c9c3419bfb1333196bf7ee469590a8303abc9264", "rating": 3.2, "latitude": 28.6917859, "reviews": [{"Review": "I have an thought about urologist Dr. R.k. chaudhiri.he is worse doctor. Careless ,unpleasant person.", "id": 1481001033}, {"Review": "Great team of enthusiastic doctors. ", "id": 1481825316}, {"Review": "Economical, prompt, trustworthy and Excellent Hospital.", "id": 1484132977}, {"Review": "Amazing hospital......my bro get a great birth with luxurious facalities..", "id": 1464241802}, {"Review": "pathetic hospital,,,they do business with the life of people", "id": 1481089910}], "longitude": 77.1814428, "address": "Phase 3, Ashok Vihar, Delhi, 110052, India", "international_phone_number": "+91 11 4703 0900"}]